{"nodes": [{"id": "c_users_mouni_documents_github_my_chips_sw_compiler_parser_go", "label": "parser.go", "file_type": "code", "source_file": "C:\\Users\\mouni\\Documents\\GitHub\\My-Chips\\sw\\compiler\\parser.go", "source_location": "L1"}, {"id": "compiler_model", "label": "Model", "file_type": "code", "source_file": "C:\\Users\\mouni\\Documents\\GitHub\\My-Chips\\sw\\compiler\\parser.go", "source_location": "L8"}, {"id": "compiler_layer", "label": "Layer", "file_type": "code", "source_file": "C:\\Users\\mouni\\Documents\\GitHub\\My-Chips\\sw\\compiler\\parser.go", "source_location": "L13"}, {"id": "compiler_parser_parsemodel", "label": "ParseModel()", "file_type": "code", "source_file": "C:\\Users\\mouni\\Documents\\GitHub\\My-Chips\\sw\\compiler\\parser.go", "source_location": "L21"}], "edges": [{"source": "c_users_mouni_documents_github_my_chips_sw_compiler_parser_go", "target": "go_pkg_encoding_json", "relation": "imports_from", "confidence": "EXTRACTED", "source_file": "C:\\Users\\mouni\\Documents\\GitHub\\My-Chips\\sw\\compiler\\parser.go", "source_location": "L4", "weight": 1.0, "context": "import"}, {"source": "c_users_mouni_documents_github_my_chips_sw_compiler_parser_go", "target": "go_pkg_os", "relation": "imports_from", "confidence": "EXTRACTED", "source_file": "C:\\Users\\mouni\\Documents\\GitHub\\My-Chips\\sw\\compiler\\parser.go", "source_location": "L5", "weight": 1.0, "context": "import"}, {"source": "c_users_mouni_documents_github_my_chips_sw_compiler_parser_go", "target": "compiler_model", "relation": "contains", "confidence": "EXTRACTED", "source_file": "C:\\Users\\mouni\\Documents\\GitHub\\My-Chips\\sw\\compiler\\parser.go", "source_location": "L8", "weight": 1.0}, {"source": "c_users_mouni_documents_github_my_chips_sw_compiler_parser_go", "target": "compiler_layer", "relation": "contains", "confidence": "EXTRACTED", "source_file": "C:\\Users\\mouni\\Documents\\GitHub\\My-Chips\\sw\\compiler\\parser.go", "source_location": "L13", "weight": 1.0}, {"source": "c_users_mouni_documents_github_my_chips_sw_compiler_parser_go", "target": "compiler_parser_parsemodel", "relation": "contains", "confidence": "EXTRACTED", "source_file": "C:\\Users\\mouni\\Documents\\GitHub\\My-Chips\\sw\\compiler\\parser.go", "source_location": "L21", "weight": 1.0}], "raw_calls": [{"caller_nid": "compiler_parser_parsemodel", "callee": "ReadFile", "is_member_call": false, "source_file": "C:\\Users\\mouni\\Documents\\GitHub\\My-Chips\\sw\\compiler\\parser.go", "source_location": "L22"}, {"caller_nid": "compiler_parser_parsemodel", "callee": "Unmarshal", "is_member_call": false, "source_file": "C:\\Users\\mouni\\Documents\\GitHub\\My-Chips\\sw\\compiler\\parser.go", "source_location": "L28"}]}